deployment_tools/__init__.py
deployment_tools/directory.py
deployment_tools/files.py
deployment_tools/pyshell.py
deployment_tools-0.1.5.dist-info/WHEEL
deployment_tools-0.1.5.dist-info/METADATA
deployment_tools-0.1.5.dist-info/RECORD
