Metadata-Version: 2.1
Name: deployment-tools
Version: 0.1.5
Summary: Simple to use command running tools and file transformation/move tools.
Author: Daniel Nikolaev
Author-email: toolsproed@gmail.com
Requires-Python: >=3.10,<4.0
Classifier: Programming Language :: Python :: 3
Classifier: Programming Language :: Python :: 3.10
Classifier: Programming Language :: Python :: 3.11
Requires-Dist: pyyaml (>=6.0,<7.0)
Requires-Dist: toml (>=0.10.2,<0.11.0)
